[{"name":"Apple","isHerbaMystica":false,"imagePath":"apple.png","imageUrl":"https://www.serebii.net/itemdex/sprites/apple.png","pieces":3,"totalTypeBoosts":{"Flying":21,"Steel":21,"Ice":21},"totalFlavorBoosts":{"Sweet":12,"Sour":9,"Bitter":3},"totalMealPowerBoosts":{"Egg":12,"Catch":-3,"Item":21,"Humungo":-15},"typeVector":[0,0,21,0,0,0,0,0,21,0,0,0,0,0,21,0,0,0],"baseMealPowerVector":[12,-3,0,21,0,0,0,-15,0,0],"ingredientType":"filling"},{"name":"Avocado","isHerbaMystica":false,"imagePath":"avocado.png","imageUrl":"https://www.serebii.net/itemdex/sprites/avocado.png","pieces":3,"totalTypeBoosts":{"Dragon":18},"totalFlavorBoosts":{"Sweet":9,"Sour":3},"totalMealPowerBoosts":{"Catch":12,"Raid":-3,"Encounter":21},"typeVector":[0,0,0,0,0,0,0,0,0,0,0,0,0,0,0,18,0,0],"baseMealPowerVector":[0,12,0,0,-3,0,0,0,0,21],"ingredientType":"filling"},{"name":"Bacon","isHerbaMystica":false,"imagePath":"bacon.png","imageUrl":"https://www.serebii.net/itemdex/sprites/bacon.png","pieces":3,"totalTypeBoosts":{"Rock":18},"totalFlavorBoosts":{"Sweet":3,"Salty":15,"Sour":3,"Bitter":12},"totalMealPowerBoosts":{"Catch":12,"Raid":-3,"Encounter":21},"typeVector":[0,0,0,0,0,18,0,0,0,0,0,0,0,0,0,0,0,0],"baseMealPowerVector":[0,12,0,0,-3,0,0,0,0,21],"ingredientType":"filling"},{"name":"Banana","isHerbaMystica":false,"imagePath":"banana.png","imageUrl":"https://www.serebii.net/itemdex/sprites/banana.png","pieces":3,"totalTypeBoosts":{"Normal":21,"Bug":21,"Electric":21},"totalFlavorBoosts":{"Sweet":12,"Sour":3},"totalMealPowerBoosts":{"Egg":12,"Catch":-3,"Item":21,"Humungo":-15},"typeVector":[21,0,0,0,0,0,21,0,0,0,0,0,21,0,0,0,0,0],"baseMealPowerVector":[12,-3,0,21,0,0,0,-15,0,0],"ingredientType":"filling"},{"name":"Basil","isHerbaMystica":false,"imagePath":"basil.png","imageUrl":"https://www.serebii.net/itemdex/sprites/basil.png","pieces":4,"totalTypeBoosts":{"Fire":4,"Water":4,"Grass":4,"Electric":4,"Psychic":4,"Ice":4,"Dragon":4,"Dark":4,"Fairy":4},"totalFlavorBoosts":{"Salty":4,"Sour":4,"Bitter":16},"totalMealPowerBoosts":{"Egg":8,"Raid":8,"Encounter":-8},"typeVector":[0,0,0,0,0,0,0,0,0,4,4,4,4,4,4,4,4,4],"baseMealPowerVector":[8,0,0,0,8,0,0,0,0,-8],"ingredientType":"filling"},{"name":"Cheese","isHerbaMystica":false,"imagePath":"cheese.png","imageUrl":"https://www.serebii.net/itemdex/sprites/cheese.png","pieces":3,"totalTypeBoosts":{"Normal":15,"Fighting":15,"Flying":15,"Poison":15,"Ground":15,"Rock":15,"Bug":15,"Ghost":15,"Steel":15,"Fire":15,"Water":15,"Grass":15,"Electric":15,"Psychic":15,"Ice":15,"Dragon":15,"Dark":15,"Fairy":15},"totalFlavorBoosts":{"Sweet":3,"Salty":9},"totalMealPowerBoosts":{"Catch":6,"Exp":6,"Item":6,"Encounter":-6},"typeVector":[15,15,15,15,15,15,15,15,15,15,15,15,15,15,15,15,15,15],"baseMealPowerVector":[0,6,6,6,0,0,0,0,0,-6],"ingredientType":"filling"},{"name":"Cherry Tomatoes","isHerbaMystica":false,"imagePath":"cherrytomatoes.png","imageUrl":"https://www.serebii.net/itemdex/sprites/cherrytomatoes.png","pieces":3,"totalTypeBoosts":{"Bug":18},"totalFlavorBoosts":{"Sweet":9,"Sour":15,"Bitter":3},"totalMealPowerBoosts":{"Catch":12,"Raid":-3,"Encounter":21},"typeVector":[0,0,0,0,0,0,18,0,0,0,0,0,0,0,0,0,0,0],"baseMealPowerVector":[0,12,0,0,-3,0,0,0,0,21],"ingredientType":"filling"},{"name":"Chorizo","isHerbaMystica":false,"imagePath":"chorizo.png","imageUrl":"https://www.serebii.net/itemdex/sprites/chorizo.png","pieces":3,"totalTypeBoosts":{"Normal":36,"Poison":36,"Bug":36,"Fire":36,"Electric":36,"Dragon":36},"totalFlavorBoosts":{"Salty":12,"Bitter":6,"Hot":12},"totalMealPowerBoosts":{"Exp":21,"Item":-3,"Encounter":12},"typeVector":[36,0,0,36,0,0,36,0,0,36,0,0,36,0,0,36,0,0],"baseMealPowerVector":[0,0,21,-3,0,0,0,0,0,12],"ingredientType":"filling"},{"name":"Cucumber","isHerbaMystica":false,"imagePath":"cucumber.png","imageUrl":"https://www.serebii.net/itemdex/sprites/cucumber.png","pieces":3,"totalTypeBoosts":{"Water":18},"totalFlavorBoosts":{"Sour":3,"Bitter":3},"totalMealPowerBoosts":{"Catch":12,"Raid":-3,"Encounter":21},"typeVector":[0,0,0,0,0,0,0,0,0,0,18,0,0,0,0,0,0,0],"baseMealPowerVector":[0,12,0,0,-3,0,0,0,0,21],"ingredientType":"filling"},{"name":"Egg","isHerbaMystica":false,"imagePath":"egg.png","imageUrl":"https://www.serebii.net/itemdex/sprites/egg.png","pieces":3,"totalTypeBoosts":{"Flying":36,"Rock":36,"Steel":36,"Grass":36,"Ice":36,"Fairy":36},"totalFlavorBoosts":{"Sweet":3,"Salty":6,"Bitter":3},"totalMealPowerBoosts":{"Exp":21,"Item":-3,"Encounter":12},"typeVector":[0,0,36,0,0,36,0,0,36,0,0,36,0,0,36,0,0,36],"baseMealPowerVector":[0,0,21,-3,0,0,0,0,0,12],"ingredientType":"filling"},{"name":"Fried Fillet","isHerbaMystica":false,"imagePath":"friedfillet.png","imageUrl":"https://www.serebii.net/itemdex/sprites/friedfillet.png","pieces":1,"totalTypeBoosts":{"Normal":20,"Flying":20,"Ground":20,"Bug":20,"Steel":20,"Water":20,"Electric":20,"Ice":20,"Dark":20},"totalFlavorBoosts":{"Sweet":2,"Salty":3,"Bitter":3},"totalMealPowerBoosts":{"Catch":21,"Raid":12,"Encounter":-3},"typeVector":[20,0,20,0,20,0,20,0,20,0,20,0,20,0,20,0,20,0],"baseMealPowerVector":[0,21,0,0,12,0,0,0,0,-3],"ingredientType":"filling"},{"name":"Green Bell Pepper","isHerbaMystica":false,"imagePath":"greenbellpepper.png","imageUrl":"https://www.serebii.net/itemdex/sprites/greenbellpepper.png","pieces":3,"totalTypeBoosts":{"Poison":18},"totalFlavorBoosts":{"Sweet":3,"Sour":3,"Bitter":15},"totalMealPowerBoosts":{"Catch":12,"Raid":-3,"Encounter":21},"typeVector":[0,0,0,18,0,0,0,0,0,0,0,0,0,0,0,0,0,0],"baseMealPowerVector":[0,12,0,0,-3,0,0,0,0,21],"ingredientType":"filling"},{"name":"Ham","isHerbaMystica":false,"imagePath":"ham.png","imageUrl":"https://www.serebii.net/itemdex/sprites/ham.png","pieces":3,"totalTypeBoosts":{"Ground":18},"totalFlavorBoosts":{"Sweet":3,"Salty":15},"totalMealPowerBoosts":{"Catch":12,"Raid":-3,"Encounter":21},"typeVector":[0,0,0,0,18,0,0,0,0,0,0,0,0,0,0,0,0,0],"baseMealPowerVector":[0,12,0,0,-3,0,0,0,0,21],"ingredientType":"filling"},{"name":"Hamburger","isHerbaMystica":false,"imagePath":"hamburger.png","imageUrl":"https://www.serebii.net/itemdex/sprites/hamburger.png","pieces":1,"totalTypeBoosts":{"Steel":18},"totalFlavorBoosts":{"Sweet":6,"Salty":12,"Bitter":9},"totalMealPowerBoosts":{"Catch":12,"Raid":-3,"Encounter":21},"typeVector":[0,0,0,0,0,0,0,0,18,0,0,0,0,0,0,0,0,0],"baseMealPowerVector":[0,12,0,0,-3,0,0,0,0,21],"ingredientType":"filling"},{"name":"Herbed Sausage","isHerbaMystica":false,"imagePath":"herbedsausage.png","imageUrl":"https://www.serebii.net/itemdex/sprites/herbedsausage.png","pieces":3,"totalTypeBoosts":{"Fighting":36,"Ground":36,"Ghost":36,"Water":36,"Psychic":36,"Dark":36},"totalFlavorBoosts":{"Sweet":3,"Salty":12,"Bitter":12},"totalMealPowerBoosts":{"Exp":21,"Item":-3,"Encounter":12},"typeVector":[0,36,0,0,36,0,0,36,0,0,36,0,0,36,0,0,36,0],"baseMealPowerVector":[0,0,21,-3,0,0,0,0,0,12],"ingredientType":"filling"},{"name":"Jalapeno","isHerbaMystica":false,"imagePath":"jalapeno.png","imageUrl":"https://www.serebii.net/itemdex/sprites/jalapeno.png","pieces":3,"totalTypeBoosts":{"Rock":21,"Grass":21,"Fairy":21},"totalFlavorBoosts":{"Sour":6,"Hot":15},"totalMealPowerBoosts":{"Egg":12,"Catch":-3,"Item":21,"Humungo":-15},"typeVector":[0,0,0,0,0,21,0,0,0,0,0,21,0,0,0,0,0,21],"baseMealPowerVector":[12,-3,0,21,0,0,0,-15,0,0],"ingredientType":"filling"},{"name":"Kiwi","isHerbaMystica":false,"imagePath":"kiwi.png","imageUrl":"https://www.serebii.net/itemdex/sprites/kiwi.png","pieces":3,"totalTypeBoosts":{"Poison":21,"Fire":21,"Dragon":21},"totalFlavorBoosts":{"Sweet":6,"Sour":15,"Bitter":3},"totalMealPowerBoosts":{"Egg":12,"Catch":-3,"Item":21,"Humungo":-15},"typeVector":[0,0,0,21,0,0,0,0,0,21,0,0,0,0,0,21,0,0],"baseMealPowerVector":[12,-3,0,21,0,0,0,-15,0,0],"ingredientType":"filling"},{"name":"Klawf Stick","isHerbaMystica":false,"imagePath":"klawfstick.png","imageUrl":"https://www.serebii.net/itemdex/sprites/klawfstick.png","pieces":3,"totalTypeBoosts":{"Ice":18},"totalFlavorBoosts":{"Sweet":12,"Salty":12},"totalMealPowerBoosts":{"Catch":12,"Raid":-3,"Encounter":21},"typeVector":[0,0,0,0,0,0,0,0,0,0,0,0,0,0,18,0,0,0],"baseMealPowerVector":[0,12,0,0,-3,0,0,0,0,21],"ingredientType":"filling"},{"name":"Lettuce","isHerbaMystica":false,"imagePath":"lettuce.png","imageUrl":"https://www.serebii.net/itemdex/sprites/lettuce.png","pieces":3,"totalTypeBoosts":{"Grass":18},"totalFlavorBoosts":{"Sweet":3,"Bitter":6},"totalMealPowerBoosts":{"Catch":12,"Raid":-3,"Encounter":21},"typeVector":[0,0,0,0,0,0,0,0,0,0,0,18,0,0,0,0,0,0],"baseMealPowerVector":[0,12,0,0,-3,0,0,0,0,21],"ingredientType":"filling"},{"name":"Noodles","isHerbaMystica":false,"imagePath":"noodles.png","imageUrl":"https://www.serebii.net/itemdex/sprites/noodles.png","pieces":1,"totalTypeBoosts":{"Poison":30,"Ground":30,"Rock":30,"Electric":30,"Psychic":30,"Ice":30},"totalFlavorBoosts":{"Salty":4},"totalMealPowerBoosts":{"Humungo":21,"Teensy":-3,"Encounter":12},"typeVector":[0,0,0,30,30,30,0,0,0,0,0,0,30,30,30,0,0,0],"baseMealPowerVector":[0,0,0,0,0,0,0,21,-3,12],"ingredientType":"filling"},{"name":"Onion","isHerbaMystica":false,"imagePath":"onion.png","imageUrl":"https://www.serebii.net/itemdex/sprites/onion.png","pieces":3,"totalTypeBoosts":{"Psychic":18},"totalFlavorBoosts":{"Sweet":6,"Bitter":3,"Hot":9},"totalMealPowerBoosts":{"Catch":12,"Raid":-3,"Encounter":21},"typeVector":[0,0,0,0,0,0,0,0,0,0,0,0,0,18,0,0,0,0],"baseMealPowerVector":[0,12,0,0,-3,0,0,0,0,21],"ingredientType":"filling"},{"name":"Pickle","isHerbaMystica":false,"imagePath":"pickle.png","imageUrl":"https://www.serebii.net/itemdex/sprites/pickle.png","pieces":3,"totalTypeBoosts":{"Fighting":18},"totalFlavorBoosts":{"Sweet":3,"Sour":12,"Bitter":6},"totalMealPowerBoosts":{"Catch":12,"Raid":-3,"Encounter":21},"typeVector":[0,18,0,0,0,0,0,0,0,0,0,0,0,0,0,0,0,0],"baseMealPowerVector":[0,12,0,0,-3,0,0,0,0,21],"ingredientType":"filling"},{"name":"Pineapple","isHerbaMystica":false,"imagePath":"pineapple.png","imageUrl":"https://www.serebii.net/itemdex/sprites/pineapple.png","pieces":3,"totalTypeBoosts":{"Ground":21,"Water":21,"Dark":21},"totalFlavorBoosts":{"Sweet":9,"Sour":15,"Bitter":3},"totalMealPowerBoosts":{"Egg":12,"Catch":-3,"Item":21,"Humungo":-15},"typeVector":[0,0,0,0,21,0,0,0,0,0,21,0,0,0,0,0,21,0],"baseMealPowerVector":[12,-3,0,21,0,0,0,-15,0,0],"ingredientType":"filling"},{"name":"Potato Salad","isHerbaMystica":false,"imagePath":"potatosalad.png","imageUrl":"https://www.serebii.net/itemdex/sprites/potatosalad.png","pieces":1,"totalTypeBoosts":{"Bug":30,"Ghost":30,"Steel":30,"Dragon":30,"Dark":30,"Fairy":30},"totalFlavorBoosts":{"Sweet":2,"Salty":3,"Sour":4,"Bitter":1},"totalMealPowerBoosts":{"Humungo":21,"Teensy":-3,"Encounter":12},"typeVector":[0,0,0,0,0,0,30,30,30,0,0,0,0,0,0,30,30,30],"baseMealPowerVector":[0,0,0,0,0,0,0,21,-3,12],"ingredientType":"filling"},{"name":"Potato Tortilla","isHerbaMystica":false,"imagePath":"potatotortilla.png","imageUrl":"https://www.serebii.net/itemdex/sprites/potatotortilla.png","pieces":1,"totalTypeBoosts":{"Fighting":20,"Poison":20,"Rock":20,"Ghost":20,"Fire":20,"Grass":20,"Psychic":20,"Dragon":20,"Fairy":20},"totalFlavorBoosts":{"Sweet":3,"Salty":4,"Sour":1,"Bitter":3,"Hot":1},"totalMealPowerBoosts":{"Catch":21,"Raid":12,"Encounter":-3},"typeVector":[0,20,0,20,0,20,0,20,0,20,0,20,0,20,0,20,0,20],"baseMealPowerVector":[0,21,0,0,12,0,0,0,0,-3],"ingredientType":"filling"},{"name":"Prosciutto","isHerbaMystica":false,"imagePath":"prosciutto.png","imageUrl":"https://www.serebii.net/itemdex/sprites/prosciutto.png","pieces":3,"totalTypeBoosts":{"Flying":18},"totalFlavorBoosts":{"Sweet":6,"Salty":12,"Sour":3},"totalMealPowerBoosts":{"Catch":12,"Raid":-3,"Encounter":21},"typeVector":[0,0,18,0,0,0,0,0,0,0,0,0,0,0,0,0,0,0],"baseMealPowerVector":[0,12,0,0,-3,0,0,0,0,21],"ingredientType":"filling"},{"name":"Red Bell Pepper","isHerbaMystica":false,"imagePath":"redbellpepper.png","imageUrl":"https://www.serebii.net/itemdex/sprites/redbellpepper.png","pieces":3,"totalTypeBoosts":{"Fire":18},"totalFlavorBoosts":{"Sweet":3,"Sour":3,"Bitter":9},"totalMealPowerBoosts":{"Catch":12,"Raid":-3,"Encounter":21},"typeVector":[0,0,0,0,0,0,0,0,0,18,0,0,0,0,0,0,0,0],"baseMealPowerVector":[0,12,0,0,-3,0,0,0,0,21],"ingredientType":"filling"},{"name":"Red Onion","isHerbaMystica":false,"imagePath":"redonion.png","imageUrl":"https://www.serebii.net/itemdex/sprites/redonion.png","pieces":3,"totalTypeBoosts":{"Ghost":18},"totalFlavorBoosts":{"Sweet":9,"Bitter":3},"totalMealPowerBoosts":{"Catch":12,"Raid":-3,"Encounter":21},"typeVector":[0,0,0,0,0,0,0,18,0,0,0,0,0,0,0,0,0,0],"baseMealPowerVector":[0,12,0,0,-3,0,0,0,0,21],"ingredientType":"filling"},{"name":"Rice","isHerbaMystica":false,"imagePath":"rice.png","imageUrl":"https://www.serebii.net/itemdex/sprites/rice.png","pieces":1,"totalTypeBoosts":{"Normal":30,"Fighting":30,"Flying":30,"Fire":30,"Water":30,"Grass":30},"totalFlavorBoosts":{"Sweet":3,"Sour":1},"totalMealPowerBoosts":{"Humungo":21,"Teensy":-3,"Encounter":12},"typeVector":[30,30,30,0,0,0,0,0,0,30,30,30,0,0,0,0,0,0],"baseMealPowerVector":[0,0,0,0,0,0,0,21,-3,12],"ingredientType":"filling"},{"name":"Smoked Fillet","isHerbaMystica":false,"imagePath":"smokedfillet.png","imageUrl":"https://www.serebii.net/itemdex/sprites/smokedfillet.png","pieces":3,"totalTypeBoosts":{"Dark":18},"totalFlavorBoosts":{"Sweet":3,"Salty":9,"Sour":6,"Bitter":9},"totalMealPowerBoosts":{"Catch":12,"Raid":-3,"Encounter":21},"typeVector":[0,0,0,0,0,0,0,0,0,0,0,0,0,0,0,0,18,0],"baseMealPowerVector":[0,12,0,0,-3,0,0,0,0,21],"ingredientType":"filling"},{"name":"Strawberry","isHerbaMystica":false,"imagePath":"strawberry.png","imageUrl":"https://www.serebii.net/itemdex/sprites/strawberry.png","pieces":3,"totalTypeBoosts":{"Fighting":21,"Ghost":21,"Psychic":21},"totalFlavorBoosts":{"Sweet":12,"Sour":12},"totalMealPowerBoosts":{"Egg":12,"Catch":-3,"Item":21,"Humungo":-15},"typeVector":[0,21,0,0,0,0,0,21,0,0,0,0,0,21,0,0,0,0],"baseMealPowerVector":[12,-3,0,21,0,0,0,-15,0,0],"ingredientType":"filling"},{"name":"Tofu","isHerbaMystica":false,"imagePath":"tofu.png","imageUrl":"https://www.serebii.net/itemdex/sprites/tofu.png","pieces":3,"totalTypeBoosts":{"Normal":18},"totalFlavorBoosts":{"Sweet":9},"totalMealPowerBoosts":{"Catch":12,"Raid":-3,"Encounter":21},"typeVector":[18,0,0,0,0,0,0,0,0,0,0,0,0,0,0,0,0,0],"baseMealPowerVector":[0,12,0,0,-3,0,0,0,0,21],"ingredientType":"filling"},{"name":"Tomato","isHerbaMystica":false,"imagePath":"tomato.png","imageUrl":"https://www.serebii.net/itemdex/sprites/tomato.png","pieces":3,"totalTypeBoosts":{"Fairy":18},"totalFlavorBoosts":{"Sweet":6,"Sour":12,"Bitter":3},"totalMealPowerBoosts":{"Catch":12,"Raid":-3,"Encounter":21},"typeVector":[0,0,0,0,0,0,0,0,0,0,0,0,0,0,0,0,0,18],"baseMealPowerVector":[0,12,0,0,-3,0,0,0,0,21],"ingredientType":"filling"},{"name":"Watercress","isHerbaMystica":false,"imagePath":"watercress.png","imageUrl":"https://www.serebii.net/itemdex/sprites/watercress.png","pieces":3,"totalTypeBoosts":{"Normal":3,"Fighting":3,"Flying":3,"Poison":3,"Ground":3,"Rock":3,"Bug":3,"Ghost":3,"Steel":3},"totalFlavorBoosts":{"Salty":3,"Sour":6,"Bitter":15,"Hot":3},"totalMealPowerBoosts":{"Egg":6,"Raid":6,"Encounter":-6},"typeVector":[3,3,3,3,3,3,3,3,3,0,0,0,0,0,0,0,0,0],"baseMealPowerVector":[6,0,0,0,6,0,0,0,0,-6],"ingredientType":"filling"},{"name":"Yellow Bell Pepper","isHerbaMystica":false,"imagePath":"yellowbellpepper.png","imageUrl":"https://www.serebii.net/itemdex/sprites/yellowbellpepper.png","pieces":3,"totalTypeBoosts":{"Electric":18},"totalFlavorBoosts":{"Sweet":3,"Sour":3,"Bitter":9},"totalMealPowerBoosts":{"Catch":12,"Raid":-3,"Encounter":21},"typeVector":[0,0,0,0,0,0,0,0,0,0,0,0,18,0,0,0,0,0],"baseMealPowerVector":[0,12,0,0,-3,0,0,0,0,21],"ingredientType":"filling"},{"name":"Butter","isHerbaMystica":false,"imagePath":"butter.png","imageUrl":"https://www.serebii.net/itemdex/sprites/butter.png","pieces":1,"totalMealPowerBoosts":{"Egg":-3,"Exp":12,"Raid":21},"totalTypeBoosts":{"Bug":2,"Ghost":2},"totalFlavorBoosts":{"Sweet":12,"Salty":12},"typeVector":[0,0,0,0,0,0,2,2,0,0,0,0,0,0,0,0,0,0],"baseMealPowerVector":[-3,0,12,0,21,0,0,0,0,0],"ingredientType":"condiment"},{"name":"Chili Sauce","isHerbaMystica":false,"imagePath":"chilisauce.png","imageUrl":"https://www.serebii.net/itemdex/sprites/chilisauce.png","pieces":1,"totalMealPowerBoosts":{"Egg":-3,"Exp":12,"Raid":21},"totalTypeBoosts":{"Water":2,"Grass":2},"totalFlavorBoosts":{"Sweet":8,"Salty":12,"Sour":8,"Hot":20},"typeVector":[0,0,0,0,0,0,0,0,0,0,2,2,0,0,0,0,0,0],"baseMealPowerVector":[-3,0,12,0,21,0,0,0,0,0],"ingredientType":"condiment"},{"name":"Cream Cheese","isHerbaMystica":false,"imagePath":"creamcheese.png","imageUrl":"https://www.serebii.net/itemdex/sprites/creamcheese.png","pieces":1,"totalMealPowerBoosts":{"Egg":5,"Exp":-3,"Item":12,"Teensy":-15},"totalTypeBoosts":{"Bug":4,"Steel":4,"Water":4},"totalFlavorBoosts":{"Sweet":12,"Salty":12,"Sour":12},"typeVector":[0,0,0,0,0,0,4,0,4,0,4,0,0,0,0,0,0,0],"baseMealPowerVector":[5,0,-3,12,0,0,0,0,-15,0],"ingredientType":"condiment"},{"name":"Curry Powder","isHerbaMystica":false,"imagePath":"currypowder.png","imageUrl":"https://www.serebii.net/itemdex/sprites/currypowder.png","pieces":1,"totalMealPowerBoosts":{"Humungo":-3,"Teensy":21,"Encounter":12},"totalTypeBoosts":{"Bug":2,"Ghost":2,"Steel":2,"Fire":2,"Water":2,"Grass":2},"totalFlavorBoosts":{"Sweet":4,"Salty":4,"Sour":4,"Bitter":12,"Hot":30},"typeVector":[0,0,0,0,0,0,2,2,2,2,2,2,0,0,0,0,0,0],"baseMealPowerVector":[0,0,0,0,0,0,0,-3,21,12],"ingredientType":"condiment"},{"name":"Horseradish","isHerbaMystica":false,"imagePath":"horseradish.png","imageUrl":"https://www.serebii.net/itemdex/sprites/horseradish.png","pieces":1,"totalMealPowerBoosts":{"Humungo":-3,"Teensy":21,"Encounter":12},"totalTypeBoosts":{"Normal":2,"Fighting":2,"Flying":2,"Poison":2,"Ground":2,"Rock":2},"totalFlavorBoosts":{"Sweet":4,"Hot":16},"typeVector":[2,2,2,2,2,2,0,0,0,0,0,0,0,0,0,0,0,0],"baseMealPowerVector":[0,0,0,0,0,0,0,-3,21,12],"ingredientType":"condiment"},{"name":"Jam","isHerbaMystica":false,"imagePath":"jam.png","imageUrl":"https://www.serebii.net/itemdex/sprites/jam.png","pieces":1,"totalMealPowerBoosts":{"Egg":5,"Exp":-3,"Item":12,"Teensy":-15},"totalTypeBoosts":{"Electric":4,"Ice":4,"Dark":4},"totalFlavorBoosts":{"Sweet":16,"Salty":4,"Sour":16},"typeVector":[0,0,0,0,0,0,0,0,0,0,0,0,4,0,4,0,4,0],"baseMealPowerVector":[5,0,-3,12,0,0,0,0,-15,0],"ingredientType":"condiment"},{"name":"Ketchup","isHerbaMystica":false,"imagePath":"ketchup.png","imageUrl":"https://www.serebii.net/itemdex/sprites/ketchup.png","pieces":1,"totalMealPowerBoosts":{"Egg":-3,"Exp":12,"Raid":21},"totalTypeBoosts":{"Flying":2,"Poison":2},"totalFlavorBoosts":{"Sweet":8,"Salty":16,"Sour":16},"typeVector":[0,0,2,2,0,0,0,0,0,0,0,0,0,0,0,0,0,0],"baseMealPowerVector":[-3,0,12,0,21,0,0,0,0,0],"ingredientType":"condiment"},{"name":"Marmalade","isHerbaMystica":false,"imagePath":"marmalade.png","imageUrl":"https://www.serebii.net/itemdex/sprites/marmalade.png","pieces":1,"totalMealPowerBoosts":{"Egg":5,"Exp":-3,"Item":12,"Teensy":-15},"totalTypeBoosts":{"Fighting":4,"Poison":4,"Rock":4},"totalFlavorBoosts":{"Sweet":12,"Salty":4,"Sour":16,"Bitter":20},"typeVector":[0,4,0,4,0,4,0,0,0,0,0,0,0,0,0,0,0,0],"baseMealPowerVector":[5,0,-3,12,0,0,0,0,-15,0],"ingredientType":"condiment"},{"name":"Mayonnaise","isHerbaMystica":false,"imagePath":"mayonnaise.png","imageUrl":"https://www.serebii.net/itemdex/sprites/mayonnaise.png","pieces":1,"totalMealPowerBoosts":{"Egg":-3,"Exp":12,"Raid":21},"totalTypeBoosts":{"Normal":2,"Fighting":2},"totalFlavorBoosts":{"Salty":8,"Sour":20},"typeVector":[2,2,0,0,0,0,0,0,0,0,0,0,0,0,0,0,0,0],"baseMealPowerVector":[-3,0,12,0,21,0,0,0,0,0],"ingredientType":"condiment"},{"name":"Mustard","isHerbaMystica":false,"imagePath":"mustard.png","imageUrl":"https://www.serebii.net/itemdex/sprites/mustard.png","pieces":1,"totalMealPowerBoosts":{"Egg":-3,"Exp":12,"Raid":21},"totalTypeBoosts":{"Ground":2,"Rock":2},"totalFlavorBoosts":{"Sweet":4,"Salty":8,"Sour":8,"Bitter":8,"Hot":16},"typeVector":[0,0,0,0,2,2,0,0,0,0,0,0,0,0,0,0,0,0],"baseMealPowerVector":[-3,0,12,0,21,0,0,0,0,0],"ingredientType":"condiment"},{"name":"Olive Oil","isHerbaMystica":false,"imagePath":"oliveoil.png","imageUrl":"https://www.serebii.net/itemdex/sprites/oliveoil.png","pieces":1,"totalMealPowerBoosts":{"Egg":5,"Exp":-3,"Item":12,"Teensy":-15},"totalTypeBoosts":{"Ghost":4,"Fire":4,"Grass":4},"totalFlavorBoosts":{"Sour":4,"Bitter":4},"typeVector":[0,0,0,0,0,0,0,4,0,4,0,4,0,0,0,0,0,0],"baseMealPowerVector":[5,0,-3,12,0,0,0,0,-15,0],"ingredientType":"condiment"},{"name":"Peanut Butter","isHerbaMystica":false,"imagePath":"peanutbutter.png","imageUrl":"https://www.serebii.net/itemdex/sprites/peanutbutter.png","pieces":1,"totalMealPowerBoosts":{"Egg":-3,"Exp":12,"Raid":21},"totalTypeBoosts":{"Steel":2,"Fire":2},"totalFlavorBoosts":{"Sweet":16,"Salty":12},"typeVector":[0,0,0,0,0,0,0,0,2,2,0,0,0,0,0,0,0,0],"baseMealPowerVector":[-3,0,12,0,21,0,0,0,0,0],"ingredientType":"condiment"},{"name":"Pepper","isHerbaMystica":false,"imagePath":"pepper.png","imageUrl":"https://www.serebii.net/itemdex/sprites/pepper.png","pieces":1,"totalMealPowerBoosts":{"Egg":-3,"Exp":12,"Raid":21},"totalTypeBoosts":{"Ice":2,"Dragon":2},"totalFlavorBoosts":{"Salty":4,"Bitter":8,"Hot":16},"typeVector":[0,0,0,0,0,0,0,0,0,0,0,0,0,0,2,2,0,0],"baseMealPowerVector":[-3,0,12,0,21,0,0,0,0,0],"ingredientType":"condiment"},{"name":"Salt","isHerbaMystica":false,"imagePath":"salt.png","imageUrl":"https://www.serebii.net/itemdex/sprites/salt.png","pieces":1,"totalMealPowerBoosts":{"Egg":-3,"Exp":12,"Raid":21},"totalTypeBoosts":{"Electric":2,"Psychic":2},"totalFlavorBoosts":{"Salty":20,"Bitter":4},"typeVector":[0,0,0,0,0,0,0,0,0,0,0,0,2,2,0,0,0,0],"baseMealPowerVector":[-3,0,12,0,21,0,0,0,0,0],"ingredientType":"condiment"},{"name":"Vinegar","isHerbaMystica":false,"imagePath":"vinegar.png","imageUrl":"https://www.serebii.net/itemdex/sprites/vinegar.png","pieces":1,"totalMealPowerBoosts":{"Egg":5,"Exp":-3,"Item":12,"Teensy":-15},"totalTypeBoosts":{"Psychic":4,"Dragon":4,"Fairy":4},"totalFlavorBoosts":{"Sweet":4,"Sour":20,"Bitter":4},"typeVector":[0,0,0,0,0,0,0,0,0,0,0,0,0,4,0,4,0,4],"baseMealPowerVector":[5,0,-3,12,0,0,0,0,-15,0],"ingredientType":"condiment"},{"name":"Wasabi","isHerbaMystica":false,"imagePath":"wasabi.png","imageUrl":"https://www.serebii.net/itemdex/sprites/wasabi.png","pieces":1,"totalMealPowerBoosts":{"Humungo":-3,"Teensy":21,"Encounter":12},"totalTypeBoosts":{"Electric":2,"Psychic":2,"Ice":2,"Dragon":2,"Dark":2,"Fairy":2},"totalFlavorBoosts":{"Sweet":4,"Salty":4,"Hot":20},"typeVector":[0,0,0,0,0,0,0,0,0,0,0,0,2,2,2,2,2,2],"baseMealPowerVector":[0,0,0,0,0,0,0,-3,21,12],"ingredientType":"condiment"},{"name":"Whipped Cream","isHerbaMystica":false,"imagePath":"whippedcream.png","imageUrl":"https://www.serebii.net/itemdex/sprites/whippedcream.png","pieces":1,"totalMealPowerBoosts":{"Egg":5,"Exp":-3,"Item":12,"Teensy":-15},"totalTypeBoosts":{"Normal":4,"Flying":4,"Ground":4},"totalFlavorBoosts":{"Sweet":20},"typeVector":[4,0,4,0,4,0,0,0,0,0,0,0,0,0,0,0,0,0],"baseMealPowerVector":[5,0,-3,12,0,0,0,0,-15,0],"ingredientType":"condiment"},{"name":"Yogurt","isHerbaMystica":false,"imagePath":"yogurt.png","imageUrl":"https://www.serebii.net/itemdex/sprites/yogurt.png","pieces":1,"totalMealPowerBoosts":{"Egg":-3,"Exp":12,"Raid":21},"totalTypeBoosts":{"Dark":2,"Fairy":2},"totalFlavorBoosts":{"Sweet":16,"Sour":16},"typeVector":[0,0,0,0,0,0,0,0,0,0,0,0,0,0,0,0,2,2],"baseMealPowerVector":[-3,0,12,0,21,0,0,0,0,0],"ingredientType":"condiment"},{"name":"Bitter Herba Mystica","isHerbaMystica":true,"imagePath":"bitterherbamystica.png","imageUrl":"https://www.serebii.net/itemdex/sprites/bitterherbamystica.png","pieces":1,"totalMealPowerBoosts":{"Title":1000,"Sparkling":1000},"totalTypeBoosts":{"Normal":250,"Fighting":250,"Flying":250,"Poison":250,"Ground":250,"Rock":250,"Bug":250,"Ghost":250,"Steel":250,"Fire":250,"Water":250,"Grass":250,"Electric":250,"Psychic":250,"Ice":250,"Dragon":250,"Dark":250,"Fairy":250},"totalFlavorBoosts":{"Bitter":500},"typeVector":[250,250,250,250,250,250,250,250,250,250,250,250,250,250,250,250,250,250],"baseMealPowerVector":[0,0,0,0,0,1000,1000,0,0,0],"ingredientType":"condiment"},{"name":"Spicy Herba Mystica","isHerbaMystica":true,"imagePath":"spicyherbamystica.png","imageUrl":"https://www.serebii.net/itemdex/sprites/spicyherbamystica.png","pieces":1,"totalMealPowerBoosts":{"Title":1000,"Sparkling":1000},"totalTypeBoosts":{"Normal":250,"Fighting":250,"Flying":250,"Poison":250,"Ground":250,"Rock":250,"Bug":250,"Ghost":250,"Steel":250,"Fire":250,"Water":250,"Grass":250,"Electric":250,"Psychic":250,"Ice":250,"Dragon":250,"Dark":250,"Fairy":250},"totalFlavorBoosts":{"Hot":500},"typeVector":[250,250,250,250,250,250,250,250,250,250,250,250,250,250,250,250,250,250],"baseMealPowerVector":[0,0,0,0,0,1000,1000,0,0,0],"ingredientType":"condiment"},{"name":"Salty Herba Mystica","isHerbaMystica":true,"imagePath":"saltyherbamystica.png","imageUrl":"https://www.serebii.net/itemdex/sprites/saltyherbamystica.png","pieces":1,"totalMealPowerBoosts":{"Title":1000,"Sparkling":1000},"totalTypeBoosts":{"Normal":250,"Fighting":250,"Flying":250,"Poison":250,"Ground":250,"Rock":250,"Bug":250,"Ghost":250,"Steel":250,"Fire":250,"Water":250,"Grass":250,"Electric":250,"Psychic":250,"Ice":250,"Dragon":250,"Dark":250,"Fairy":250},"totalFlavorBoosts":{"Salty":500},"typeVector":[250,250,250,250,250,250,250,250,250,250,250,250,250,250,250,250,250,250],"baseMealPowerVector":[0,0,0,0,0,1000,1000,0,0,0],"ingredientType":"condiment"},{"name":"Sour Herba Mystica","isHerbaMystica":true,"imagePath":"sourherbamystica.png","imageUrl":"https://www.serebii.net/itemdex/sprites/sourherbamystica.png","pieces":1,"totalMealPowerBoosts":{"Title":1000,"Sparkling":1000},"totalTypeBoosts":{"Normal":250,"Fighting":250,"Flying":250,"Poison":250,"Ground":250,"Rock":250,"Bug":250,"Ghost":250,"Steel":250,"Fire":250,"Water":250,"Grass":250,"Electric":250,"Psychic":250,"Ice":250,"Dragon":250,"Dark":250,"Fairy":250},"totalFlavorBoosts":{"Sour":500},"typeVector":[250,250,250,250,250,250,250,250,250,250,250,250,250,250,250,250,250,250],"baseMealPowerVector":[0,0,0,0,0,1000,1000,0,0,0],"ingredientType":"condiment"},{"name":"Sweet Herba Mystica","isHerbaMystica":true,"imagePath":"sweetherbamystica.png","imageUrl":"https://www.serebii.net/itemdex/sprites/sweetherbamystica.png","pieces":1,"totalMealPowerBoosts":{"Title":1000,"Sparkling":1000},"totalTypeBoosts":{"Normal":250,"Fighting":250,"Flying":250,"Poison":250,"Ground":250,"Rock":250,"Bug":250,"Ghost":250,"Steel":250,"Fire":250,"Water":250,"Grass":250,"Electric":250,"Psychic":250,"Ice":250,"Dragon":250,"Dark":250,"Fairy":250},"totalFlavorBoosts":{"Sweet":500},"typeVector":[250,250,250,250,250,250,250,250,250,250,250,250,250,250,250,250,250,250],"baseMealPowerVector":[0,0,0,0,0,1000,1000,0,0,0],"ingredientType":"condiment"}]